sequencing_table_one/__init__.py
sequencing_table_one/frontend/build/asset-manifest.json
sequencing_table_one/frontend/build/bootstrap.min.css
sequencing_table_one/frontend/build/index.html
sequencing_table_one/frontend/build/static/css/main.445667d6.css
sequencing_table_one/frontend/build/static/css/main.445667d6.css.map
sequencing_table_one/frontend/build/static/js/main.a02a2876.js
sequencing_table_one/frontend/build/static/js/main.a02a2876.js.LICENSE.txt
sequencing_table_one/frontend/build/static/js/main.a02a2876.js.map
sequencing_table_one-2.0.0.dist-info/METADATA
sequencing_table_one-2.0.0.dist-info/WHEEL
sequencing_table_one-2.0.0.dist-info/top_level.txt
sequencing_table_one-2.0.0.dist-info/RECORD
