Metadata-Version: 2.1
Name: sequencing-table-one
Version: 2.0.0
Home-page: 
Author: 
Author-email: 
Requires-Python: >=3.6
Requires-Dist: streamlit >=0.66
